pymint/__init__.py
pymint/common/__init__.py
pymint/common/attributes.py
pymint/common/dataset.py
pymint/common/models.py
pymint/common/multiprocessing_utils.py
pymint/common/utils.py
pymint/common/data/data_for_mintpy.csv
pymint/common/models/GradientBoostingClassifier.pkl
pymint/common/models/LogisticRegression.pkl
pymint/common/models/RandomForestClassifier.pkl
pymint/main/__init__.py
pymint/main/global_interpret.py
pymint/main/interpret_toolkit.py
pymint/main/local_interpret.py
pymint/main/tree_interpreter.py
pymint/main/PermutationImportance/__init__.py
pymint/main/PermutationImportance/abstract_runner.py
pymint/main/PermutationImportance/data_verification.py
pymint/main/PermutationImportance/error_handling.py
pymint/main/PermutationImportance/metrics.py
pymint/main/PermutationImportance/multiprocessing_utils.py
pymint/main/PermutationImportance/permutation_importance.py
pymint/main/PermutationImportance/result.py
pymint/main/PermutationImportance/scoring_strategies.py
pymint/main/PermutationImportance/selection_strategies.py
pymint/main/PermutationImportance/sequential_selection.py
pymint/main/PermutationImportance/sklearn_api.py
pymint/main/PermutationImportance/utils.py
pymint/plot/__init__.py
pymint/plot/_box_and_whisker.py
pymint/plot/_kde_2d.py
pymint/plot/base_plotting.py
pymint/plot/dependence.py
pymint/plot/plot_2D.py
pymint/plot/plot_feature_contributions.py
pymint/plot/plot_interpret_curves.py
pymint/plot/plot_permutation_importance.py
py_mint-0.2.6.dist-info/LICENSE
py_mint-0.2.6.dist-info/METADATA
py_mint-0.2.6.dist-info/WHEEL
py_mint-0.2.6.dist-info/top_level.txt
py_mint-0.2.6.dist-info/RECORD
